{"1": {"object": {"parent": "NoReply", "author": "https://twitter.com/intent/user?user_id=1583980482", "text": "RT @MHEducation: Education is changing. So are we. How we bring the science of learning to the art of teaching: https://t.co/cacv0b7nG7 #K1\u2026", "hashtags": ["K12", "College", "Career"], "author_alias": "MHECareers", "author_name": "McGraw-Hill Careers", "user_mentions": ["90961345"], "to": "NoReply", "tweet_sentiment": "0.292102", "subtype": "tweet", "tweet_id": "578935654014267393", "@id": "https://twitter.com/MHECareers/status/578935654014267393", "@type": "MessagingEvent"}, "startedAtTime": {"$date": 1426863990000}, "verb": "tweetSent", "actor": "student:MHECareers", "@context": "http://purl.imsglobal.org/ctx/caliper/v1/MessagingEvent", "_id": {"$oid": "5513117ab82c8508e5a56e09"}, "@type": "MessagingEvent"}, "2": {"object": {"parent": "NoReply", "author": "https://twitter.com/intent/user?user_id=1573081519", "text": "RT @bookbusinessmag: Very excited for this event! @PerseusBooks @MHEducation @HachetteUS round out speaker roster at Book Business Live htt\u2026", "hashtags": [], "author_alias": "4SquareBooks", "author_name": "4 Square Books", "user_mentions": ["55245430", "2353608811", "90961345", "112796663"], "to": "NoReply", "tweet_sentiment": "0.540208", "subtype": "tweet", "tweet_id": "578930987255652352", "@id": "https://twitter.com/4SquareBooks/status/578930987255652352", "@type": "MessagingEvent"}, "startedAtTime": {"$date": 1426862878000}, "verb": "tweetSent", "actor": "student:4SquareBooks", "@context": "http://purl.imsglobal.org/ctx/caliper/v1/MessagingEvent", "_id": {"$oid": "5513117bb82c8508e5a56e0a"}, "@type": "MessagingEvent"}, "3": {"object": {"parent": "NoReply", "author": "https://twitter.com/intent/user?user_id=17350185", "text": "Very excited for this event! @PerseusBooks @MHEducation @HachetteUS round out speaker roster at Book Business Live http://t.co/GQZY7KnZwt", "hashtags": [], "author_alias": "pubbusiness", "author_name": "pubbusiness", "user_mentions": ["2353608811", "90961345", "112796663"], "to": "NoReply", "tweet_sentiment": "0.555379", "subtype": "tweet", "tweet_id": "578924613478064128", "@id": "https://twitter.com/pubbusiness/status/578924613478064128", "@type": "MessagingEvent"}, "startedAtTime": {"$date": 1426861358000}, "verb": "tweetSent", "actor": "student:pubbusiness", "@context": "http://purl.imsglobal.org/ctx/caliper/v1/MessagingEvent", "_id": {"$oid": "5513117bb82c8508e5a56e0b"}, "@type": "MessagingEvent"}, "4": {"object": {"parent": "NoReply", "author": "https://twitter.com/intent/user?user_id=55245430", "text": "Very excited for this event! @PerseusBooks @MHEducation @HachetteUS round out speaker roster at Book Business Live http://t.co/xXgYKliVqv", "hashtags": [], "author_alias": "bookbusinessmag", "author_name": "Book Business", "user_mentions": ["2353608811", "90961345", "112796663"], "to": "NoReply", "tweet_sentiment": "0.555379", "subtype": "tweet", "tweet_id": "578924613461233664", "@id": "https://twitter.com/bookbusinessmag/status/578924613461233664", "@type": "MessagingEvent"}, "startedAtTime": {"$date": 1426861358000}, "verb": "tweetSent", "actor": "student:bookbusinessmag", "@context": "http://purl.imsglobal.org/ctx/caliper/v1/MessagingEvent", "_id": {"$oid": "5513117bb82c8508e5a56e0c"}, "@type": "MessagingEvent"}, "5": {"object": {"parent": "NoReply", "author": "https://twitter.com/intent/user?user_id=604020650", "text": "RT @MHEducation: \u201cIf winter comes, can spring be far behind?\u201d  -Shelley | Happy first day of #spring 2015! #equinox #edchat #quote http://t\u2026", "hashtags": ["spring", "equinox", "edchat", "quote"], "author_alias": "ScienceIsAVerb1", "author_name": "ScienceIsAVerb", "user_mentions": ["90961345"], "to": "NoReply", "tweet_sentiment": "0.390864", "subtype": "tweet", "tweet_id": "578909254481940480", "@id": "https://twitter.com/ScienceIsAVerb1/status/578909254481940480", "@type": "MessagingEvent"}, "startedAtTime": {"$date": 1426857696000}, "verb": "tweetSent", "actor": "student:ScienceIsAVerb1", "@context": "http://purl.imsglobal.org/ctx/caliper/v1/MessagingEvent", "_id": {"$oid": "5513117bb82c8508e5a56e0d"}, "@type": "MessagingEvent"}, "6": {"object": {"parent": "NoReply", "author": "https://twitter.com/intent/user?user_id=1363123478", "text": "RT @Bob_Wachter: My \"book video\" http://t.co/ZzqE391aPu: why I wrote #DigitalDoc; will computrs replace MDs; why, despite problms, Im optim\u2026", "hashtags": ["DigitalDoc"], "author_alias": "SethBokserMD", "author_name": "Dr. Seth Bokser", "user_mentions": ["239210681", "90961345"], "to": "NoReply", "tweet_sentiment": "0.390864", "subtype": "tweet", "tweet_id": "578830159375003648", "@id": "https://twitter.com/SethBokserMD/status/578830159375003648", "@type": "MessagingEvent"}, "startedAtTime": {"$date": 1426838838000}, "verb": "tweetSent", "actor": "student:SethBokserMD", "@context": "http://purl.imsglobal.org/ctx/caliper/v1/MessagingEvent", "_id": {"$oid": "5513117bb82c8508e5a56e0e"}, "@type": "MessagingEvent"}, "7": {"object": {"parent": "NoReply", "author": "https://twitter.com/intent/user?user_id=120957858", "text": "RT @MHEducation: A look at ALEKS adaptive college math in-action: http://t.co/oLs8NjiFys #mathchat #edtech http://t.co/fXpkBlKchV", "hashtags": ["mathchat", "edtech"], "author_alias": "rsamantha725", "author_name": "Samantha Rosenthal", "user_mentions": ["90961345"], "to": "NoReply", "tweet_sentiment": "0.273192", "subtype": "tweet", "tweet_id": "578786899797549058", "@id": "https://twitter.com/rsamantha725/status/578786899797549058", "@type": "MessagingEvent"}, "startedAtTime": {"$date": 1426828524000}, "verb": "tweetSent", "actor": "student:rsamantha725", "@context": "http://purl.imsglobal.org/ctx/caliper/v1/MessagingEvent", "_id": {"$oid": "5513117bb82c8508e5a56e0f"}, "@type": "MessagingEvent"}, "8": {"object": {"parent": "NoReply", "author": "https://twitter.com/intent/user?user_id=22502159", "text": "RT @MHEducation: 4 Ways You Can Still Experience #SXSWedu: http://t.co/hU2naxEYwr #edtech #edchat #innovation", "hashtags": ["SXSWedu", "edtech", "edchat", "innovation"], "author_alias": "learn8054", "author_name": "Brandon Harvey", "user_mentions": ["90961345"], "to": "NoReply", "tweet_sentiment": "0.577778", "subtype": "tweet", "tweet_id": "578782788175802368", "@id": "https://twitter.com/learn8054/status/578782788175802368", "@type": "MessagingEvent"}, "startedAtTime": {"$date": 1426827544000}, "verb": "tweetSent", "actor": "student:learn8054", "@context": "http://purl.imsglobal.org/ctx/caliper/v1/MessagingEvent", "_id": {"$oid": "5513117bb82c8508e5a56e10"}, "@type": "MessagingEvent"}, "9": {"object": {"parent": "NoReply", "author": "https://twitter.com/intent/user?user_id=1170280729", "text": "RT @MHEducation: A look at ALEKS adaptive college math in-action: http://t.co/oLs8NjiFys #mathchat #edtech http://t.co/fXpkBlKchV", "hashtags": ["mathchat", "edtech"], "author_alias": "EdTechFam", "author_name": "EdTechFam", "user_mentions": ["90961345"], "to": "NoReply", "tweet_sentiment": "0.273192", "subtype": "tweet", "tweet_id": "578778672640835585", "@id": "https://twitter.com/EdTechFam/status/578778672640835585", "@type": "MessagingEvent"}, "startedAtTime": {"$date": 1426826563000}, "verb": "tweetSent", "actor": "student:EdTechFam", "@context": "http://purl.imsglobal.org/ctx/caliper/v1/MessagingEvent", "_id": {"$oid": "5513117bb82c8508e5a56e11"}, "@type": "MessagingEvent"}, "10": {"object": {"parent": "NoReply", "author": "https://twitter.com/intent/user?user_id=81704520", "text": "RT @MHEducation: A look at ALEKS adaptive college math in-action: http://t.co/oLs8NjiFys #mathchat #edtech http://t.co/fXpkBlKchV", "hashtags": ["mathchat", "edtech"], "author_alias": "asouth27", "author_name": "April Southwood", "user_mentions": ["90961345"], "to": "NoReply", "tweet_sentiment": "0.273192", "subtype": "tweet", "tweet_id": "578753283809939456", "@id": "https://twitter.com/asouth27/status/578753283809939456", "@type": "MessagingEvent"}, "startedAtTime": {"$date": 1426820510000}, "verb": "tweetSent", "actor": "student:asouth27", "@context": "http://purl.imsglobal.org/ctx/caliper/v1/MessagingEvent", "_id": {"$oid": "5513117cb82c8508e5a56e12"}, "@type": "MessagingEvent"}, "11": {"object": {"parent": "https://twitter.com/nasfan19/status/578722398444384256", "author": "https://twitter.com/intent/user?user_id=378981048", "text": "@MHEducation @deanflorez Used ALEKS for Chemistry at CSUB. Could use some changes but for the most part great program.  Learned a lot", "hashtags": [], "author_alias": "nasfan19", "author_name": "Traci", "user_mentions": ["90961345", "15743349"], "to": "https://twitter.com/intent/user?user_id=90961345", "tweet_sentiment": "0.435311", "subtype": "tweet", "tweet_id": "578740981480038400", "@id": "https://twitter.com/nasfan19/status/578740981480038400", "@type": "MessagingEvent"}, "startedAtTime": {"$date": 1426817577000}, "verb": "tweetSent", "actor": "student:nasfan19", "@context": "http://purl.imsglobal.org/ctx/caliper/v1/MessagingEvent", "_id": {"$oid": "5513117cb82c8508e5a56e13"}, "@type": "MessagingEvent"}, "12": {"object": {"parent": "NoReply", "author": "https://twitter.com/intent/user?user_id=972777944", "text": "RT @MHEducation: Education is changing. So are we. How we bring the science of learning to the art of teaching: https://t.co/cacv0b7nG7 #K1\u2026", "hashtags": ["K12", "College", "Career"], "author_alias": "MelissaAislynn", "author_name": "Melissa Richard", "user_mentions": ["90961345"], "to": "NoReply", "tweet_sentiment": "0.292102", "subtype": "tweet", "tweet_id": "578737989536362496", "@id": "https://twitter.com/MelissaAislynn/status/578737989536362496", "@type": "MessagingEvent"}, "startedAtTime": {"$date": 1426816863000}, "verb": "tweetSent", "actor": "student:MelissaAislynn", "@context": "http://purl.imsglobal.org/ctx/caliper/v1/MessagingEvent", "_id": {"$oid": "5513117cb82c8508e5a56e14"}, "@type": "MessagingEvent"}, "13": {"object": {"parent": "NoReply", "author": "https://twitter.com/intent/user?user_id=2586242898", "text": "RT @MHEducation: A look at ALEKS adaptive college math in-action: http://t.co/oLs8NjiFys #mathchat #edtech http://t.co/fXpkBlKchV", "hashtags": ["mathchat", "edtech"], "author_alias": "EdTechExposed", "author_name": "#EdTech", "user_mentions": ["90961345"], "to": "NoReply", "tweet_sentiment": "0.273192", "subtype": "tweet", "tweet_id": "578729090213105665", "@id": "https://twitter.com/EdTechExposed/status/578729090213105665", "@type": "MessagingEvent"}, "startedAtTime": {"$date": 1426814742000}, "verb": "tweetSent", "actor": "student:EdTechExposed", "@context": "http://purl.imsglobal.org/ctx/caliper/v1/MessagingEvent", "_id": {"$oid": "5513117cb82c8508e5a56e15"}, "@type": "MessagingEvent"}, "14": {"object": {"parent": "NoReply", "author": "https://twitter.com/intent/user?user_id=898770306", "text": "RT @MHEducation: How K-12 school districts can have a big influence the future of #edtech: http://t.co/QB57ANs8PF MT @educationweek #edchat\u2026", "hashtags": ["edtech", "edchat", "sxswedu"], "author_alias": "AnneMarieBertra", "author_name": "Anne Marie Bertram", "user_mentions": ["90961345", "15147042"], "to": "NoReply", "tweet_sentiment": "0.273192", "subtype": "tweet", "tweet_id": "578725498689310721", "@id": "https://twitter.com/AnneMarieBertra/status/578725498689310721", "@type": "MessagingEvent"}, "startedAtTime": {"$date": 1426813885000}, "verb": "tweetSent", "actor": "student:AnneMarieBertra", "@context": "http://purl.imsglobal.org/ctx/caliper/v1/MessagingEvent", "_id": {"$oid": "5513117cb82c8508e5a56e16"}, "@type": "MessagingEvent"}, "15": {"object": {"parent": "https://twitter.com/hgersh2000/status/578722398444384256", "author": "https://twitter.com/intent/user?user_id=2368214436", "text": "@MHEducation Plenty of Pie- Charts. Topic 2: Displaying Data\n  \nDATA ANALYSIS: https://t.co/fWc0Iuy1Jv", "hashtags": [], "author_alias": "hgersh2000", "author_name": "STATISTICS", "user_mentions": ["90961345"], "to": "https://twitter.com/intent/user?user_id=90961345", "tweet_sentiment": "0.401868", "subtype": "tweet", "tweet_id": "578724795522543616", "@id": "https://twitter.com/hgersh2000/status/578724795522543616", "@type": "MessagingEvent"}, "startedAtTime": {"$date": 1426813718000}, "verb": "tweetSent", "actor": "student:hgersh2000", "@context": "http://purl.imsglobal.org/ctx/caliper/v1/MessagingEvent", "_id": {"$oid": "5513117cb82c8508e5a56e17"}, "@type": "MessagingEvent"}, "16": {"object": {"parent": "NoReply", "author": "https://twitter.com/intent/user?user_id=142379835", "text": "RT @MHEducation: How K-12 school districts can have a big influence the future of #edtech: http://t.co/QB57ANs8PF MT @educationweek #edchat\u2026", "hashtags": ["edtech", "edchat", "sxswedu"], "author_alias": "jcbortoni", "author_name": "Carlos Bortoni", "user_mentions": ["90961345", "15147042"], "to": "NoReply", "tweet_sentiment": "0.401868", "subtype": "tweet", "tweet_id": "578724575531397120", "@id": "https://twitter.com/jcbortoni/status/578724575531397120", "@type": "MessagingEvent"}, "startedAtTime": {"$date": 1426813665000}, "verb": "tweetSent", "actor": "student:jcbortoni", "@context": "http://purl.imsglobal.org/ctx/caliper/v1/MessagingEvent", "_id": {"$oid": "5513117cb82c8508e5a56e18"}, "@type": "MessagingEvent"}, "17": {"object": {"parent": "NoReply", "author": "https://twitter.com/intent/user?user_id=86948180", "text": "RT @MHEducation: How K-12 school districts can have a big influence the future of #edtech: http://t.co/QB57ANs8PF MT @educationweek #edchat\u2026", "hashtags": ["edtech", "edchat", "sxswedu"], "author_alias": "McGrawHillK12", "author_name": "McGraw-Hill School", "user_mentions": ["90961345", "15147042"], "to": "NoReply", "tweet_sentiment": "0.401868", "subtype": "tweet", "tweet_id": "578724278532747264", "@id": "https://twitter.com/McGrawHillK12/status/578724278532747264", "@type": "MessagingEvent"}, "startedAtTime": {"$date": 1426813594000}, "verb": "tweetSent", "actor": "student:McGrawHillK12", "@context": "http://purl.imsglobal.org/ctx/caliper/v1/MessagingEvent", "_id": {"$oid": "5513117db82c8508e5a56e19"}, "@type": "MessagingEvent"}, "18": {"object": {"parent": "NoReply", "author": "https://twitter.com/intent/user?user_id=15825051", "text": "RT @MHEducation: How K-12 school districts can have a big influence the future of #edtech: http://t.co/QB57ANs8PF MT @educationweek #edchat\u2026", "hashtags": ["edtech", "edchat", "sxswedu"], "author_alias": "RafranzDavis", "author_name": "Rafranz Davis", "user_mentions": ["90961345", "15147042"], "to": "NoReply", "tweet_sentiment": "0.401868", "subtype": "tweet", "tweet_id": "578724016698982400", "@id": "https://twitter.com/RafranzDavis/status/578724016698982400", "@type": "MessagingEvent"}, "startedAtTime": {"$date": 1426813532000}, "verb": "tweetSent", "actor": "student:RafranzDavis", "@context": "http://purl.imsglobal.org/ctx/caliper/v1/MessagingEvent", "_id": {"$oid": "5513117db82c8508e5a56e1a"}, "@type": "MessagingEvent"}, "19": {"object": {"parent": "NoReply", "author": "https://twitter.com/intent/user?user_id=15743349", "text": "RT @MHEducation: A look at ALEKS adaptive college math in-action: http://t.co/oLs8NjiFys #mathchat #edtech http://t.co/fXpkBlKchV", "hashtags": ["mathchat", "edtech"], "author_alias": "deanflorez", "author_name": "Dean Florez", "user_mentions": ["90961345"], "to": "NoReply", "tweet_sentiment": "0.273192", "subtype": "tweet", "tweet_id": "578722699620397057", "@id": "https://twitter.com/deanflorez/status/578722699620397057", "@type": "MessagingEvent"}, "startedAtTime": {"$date": 1426813218000}, "verb": "tweetSent", "actor": "student:deanflorez", "@context": "http://purl.imsglobal.org/ctx/caliper/v1/MessagingEvent", "_id": {"$oid": "5513117db82c8508e5a56e1b"}, "@type": "MessagingEvent"}, "20": {"object": {"parent": "NoReply", "author": "https://twitter.com/intent/user?user_id=135358481", "text": "Looking forward to talking about Inspire Science with New Hampshire literacy leaders Fri. Thank you Carol Cohen. @MHEducation", "hashtags": [], "author_alias": "DrNancyBoyles", "author_name": "Nancy Boyles", "user_mentions": ["90961345"], "to": "NoReply", "tweet_sentiment": "0.553177", "subtype": "tweet", "tweet_id": "578685345132363776", "@id": "https://twitter.com/DrNancyBoyles/status/578685345132363776", "@type": "MessagingEvent"}, "startedAtTime": {"$date": 1426804312000}, "verb": "tweetSent", "actor": "student:DrNancyBoyles", "@context": "http://purl.imsglobal.org/ctx/caliper/v1/MessagingEvent", "_id": {"$oid": "5513117db82c8508e5a56e1c"}, "@type": "MessagingEvent"}}